django_fast_iprestrict/__init__.py
django_fast_iprestrict/admin.py
django_fast_iprestrict/apps.py
django_fast_iprestrict/forms.py
django_fast_iprestrict/management/commands/iprestrict_clear_caches.py
django_fast_iprestrict/management/commands/iprestrict_unrestrict_all.py
django_fast_iprestrict/middleware.py
django_fast_iprestrict/migrations/0001_initial.py
django_fast_iprestrict/migrations/0002_split_rule.py
django_fast_iprestrict/migrations/0003_migrate_rule.py
django_fast_iprestrict/migrations/0004_cleanup_rule.py
django_fast_iprestrict/migrations/0005_add_ratelimit_fix_generator_fn.py
django_fast_iprestrict/migrations/0006_rule_invert_methods_rule_methods_and_more.py
django_fast_iprestrict/migrations/0007_ruleratelimitgroup_and_more.py
django_fast_iprestrict/migrations/0008_add_managed_fields.py
django_fast_iprestrict/migrations/0009_alter_ruleratelimit_rate.py
django_fast_iprestrict/migrations/0010_alter_ruleratelimit_rate.py
django_fast_iprestrict/migrations/0011_correct_ruleratelimitgroup_unique.py
django_fast_iprestrict/migrations/0012_alter_ruleratelimit_rate.py
django_fast_iprestrict/migrations/__init__.py
django_fast_iprestrict/models.py
django_fast_iprestrict/templates/admin/django_fast_iprestrict/change_list.html
django_fast_iprestrict/templates/admin/django_fast_iprestrict/lockout_prevented.html
django_fast_iprestrict/utils.py
django_fast_iprestrict/validators.py
django_fast_iprestrict-0.19.6.dist-info/LICENSE
django_fast_iprestrict-0.19.6.dist-info/METADATA
django_fast_iprestrict-0.19.6.dist-info/WHEEL
django_fast_iprestrict-0.19.6.dist-info/RECORD
