Metadata-Version: 2.1
Name: django-fast-iprestrict
Version: 0.19.6
Summary: Restrict access to django project to trusted ips and optionally apply ratelimits. Like WAF in django.
Home-page: https://github.com/devkral/django-fast-iprestrict
License: MIT
Author: alex
Author-email: devkral@web.de
Requires-Python: >=3.9,<4.0
Classifier: Development Status :: 5 - Production/Stable
Classifier: Environment :: Web Environment
Classifier: Framework :: Django
Classifier: License :: OSI Approved :: MIT License
Classifier: Programming Language :: Python :: 3
Classifier: Programming Language :: Python :: 3.9
Classifier: Programming Language :: Python :: 3.10
Classifier: Programming Language :: Python :: 3.11
Classifier: Programming Language :: Python :: 3.12
Classifier: Programming Language :: Python :: 3 :: Only
Classifier: Topic :: Security
Classifier: Topic :: System :: Networking :: Firewalls
Provides-Extra: ratelimit
Requires-Dist: django (>=4.0)
Requires-Dist: django-fast-ratelimit (>=7.3.3) ; extra == "ratelimit"
Project-URL: Repository, https://github.com/devkral/django-fast-iprestrict
